herokulls/__init__.py
herokulls/__version__.py
herokulls/binding.py
herokulls/environment.py
herokulls/exceptions.py
herokulls/ffprobe.py
herokulls/file_manager.py
herokulls/herokulls.py
herokulls/herokulls_session.py
herokulls/scaffold.py
herokulls/stream_type.py
herokulls/sync.py
herokulls/version_manager.py
herokulls/custom_api/__init__.py
herokulls/custom_api/custom_api.py
herokulls/dist/binding.js
herokulls/dist/buffer_optimized.js
herokulls/dist/ffmpeg_reader.js
herokulls/dist/file_reader.js
herokulls/dist/index.js
herokulls/dist/rtc-connection.js
herokulls/dist/sdp-builder.js
herokulls/dist/stream.js
herokulls/dist/tgcalls.js
herokulls/dist/types.js
herokulls/dist/utils.js
herokulls/handlers/__init__.py
herokulls/handlers/handlers_holder.py
herokulls/media_devices/__init__.py
herokulls/media_devices/device_info.py
herokulls/media_devices/media_devices.py
herokulls/media_devices/screen_info.py
herokulls/methods/__init__.py
herokulls/methods/core/__init__.py
herokulls/methods/core/binding_runner.py
herokulls/methods/core/join_voice_call.py
herokulls/methods/core/leave_voice_call.py
herokulls/methods/core/set_video_call_status.py
herokulls/methods/decorators/__init__.py
herokulls/methods/decorators/on_closed_voice_chat.py
herokulls/methods/decorators/on_group_call_invite.py
herokulls/methods/decorators/on_kicked.py
herokulls/methods/decorators/on_left.py
herokulls/methods/decorators/on_participants_change.py
herokulls/methods/decorators/on_raw_update.py
herokulls/methods/decorators/on_stream_end.py
herokulls/methods/groups/__init__.py
herokulls/methods/groups/active_calls.py
herokulls/methods/groups/calls.py
herokulls/methods/groups/change_volume_call.py
herokulls/methods/groups/get_active_call.py
herokulls/methods/groups/get_call.py
herokulls/methods/groups/get_participants.py
herokulls/methods/groups/join_group_call.py
herokulls/methods/groups/leave_group_call.py
herokulls/methods/handlers/__init__.py
herokulls/methods/handlers/raw_update_handler.py
herokulls-0.1.12.dist-info/licenses/LICENSE
herokulls-0.1.12.dist-info/METADATA
herokulls-0.1.12.dist-info/WHEEL
herokulls-0.1.12.dist-info/top_level.txt
herokulls-0.1.12.dist-info/RECORD
